install/.rxignore
rx/__init__.py
rx/__main__.py
rx/client/__init__.py
rx/client/browser.py
rx/client/commands/__init__.py
rx/client/commands/command.py
rx/client/commands/daemon.py
rx/client/commands/exec.py
rx/client/commands/init.py
rx/client/commands/runner.py
rx/client/commands/stop.py
rx/client/commands/subscribe.py
rx/client/commands/workspace/commit.py
rx/client/commands/workspace/info.py
rx/client/commands/workspace/port.py
rx/client/commands/workspace/set_acls.py
rx/client/commands/ws.py
rx/client/configuration/__init__.py
rx/client/configuration/config_base.py
rx/client/configuration/local.py
rx/client/configuration/remote.py
rx/client/grpc_helper.py
rx/client/login.py
rx/client/menu.py
rx/client/output_handler.py
rx/client/payment.py
rx/client/trex_client.py
rx/client/user.py
rx/client/worker_client.py
rx/daemon/__init__.py
rx/daemon/client.py
rx/daemon/daemon.py
rx/daemon/interceptors.py
rx/daemon/manager.py
rx/daemon/pidfile.py
rx/daemon/port_forwarding/__init__.py
rx/daemon/port_forwarding/client_socket.py
rx/daemon/port_forwarding/port_forwarder.py
rx/daemon/port_forwarding/service.py
rx/daemon/server.py
rx/proto/__init__.py
rx/proto/daemon_pb2.py
rx/proto/daemon_pb2.pyi
rx/proto/daemon_pb2_grpc.py
rx/proto/rx_pb2.py
rx/proto/rx_pb2.pyi
rx/proto/rx_pb2_grpc.py
rx/shared/__init__.py
rx/shared/progress_bar.py
rx/trex/__init__.py
rx/trex/toolchain/__init__.py
rx/trex/toolchain/lang_detector.py
rx/trex/toolchain/local_fs.py
rx/trex/toolchain/manifest.py
rx/trex/toolchain/toolchain.py
rx/worker/__init__.py
rx/worker/executor.py
rx/worker/rsync.py
run_rx-0.1.0.dist-info/LICENSE.txt
run_rx-0.1.0.dist-info/METADATA
run_rx-0.1.0.dist-info/WHEEL
run_rx-0.1.0.dist-info/entry_points.txt
run_rx-0.1.0.dist-info/RECORD
