Metadata-Version: 2.1
Name: run-rx
Version: 0.1.0
Summary: A tool to simplify remote execution
Home-page: https://www.run-rx.com
License: LICENSE.txt
Author: Kris Chodorow
Author-email: k.chodorow@gmail.com
Requires-Python: >=3.7,<4.0
Classifier: License :: Other/Proprietary License
Classifier: Programming Language :: Python :: 3
Classifier: Programming Language :: Python :: 3.7
Classifier: Programming Language :: Python :: 3.8
Classifier: Programming Language :: Python :: 3.9
Classifier: Programming Language :: Python :: 3.10
Classifier: Programming Language :: Python :: 3.11
Requires-Dist: PyJWT (>=2.6.0,<3.0.0)
Requires-Dist: PyYAML (>=6.0.1,<7.0.0)
Requires-Dist: absl-py (>=1.4.0,<2.0.0)
Requires-Dist: grpcio (>=1.54.0,<2.0.0)
Requires-Dist: protobuf (>=4.22.3,<5.0.0)
Requires-Dist: requests (>=2.30.0,<3.0.0)
Requires-Dist: tqdm (>=4.65.0,<5.0.0)
Project-URL: Repository, https://github.com/run-rx/rx
